setup.py
ytdown/__init__.py
ytdown/__main__.py
ytdown.egg-info/PKG-INFO
ytdown.egg-info/SOURCES.txt
ytdown.egg-info/dependency_links.txt
ytdown.egg-info/not-zip-safe
ytdown.egg-info/requires.txt
ytdown.egg-info/top_level.txt