Metadata-Version: 1.0
Name: ytdown
Version: 0.3
Summary: Download videos and audios from YouTube
Home-page: UNKNOWN
Author: Sharat
Author-email: cr.sharat@gmail.com
License: Free
Platform: UNKNOWN
